celestial/__init__.py
celestial/celestial.py
celestial_client-0.1.dist-info/LICENSE
celestial_client-0.1.dist-info/METADATA
celestial_client-0.1.dist-info/WHEEL
celestial_client-0.1.dist-info/top_level.txt
celestial_client-0.1.dist-info/RECORD
