Metadata-Version: 2.1
Name: celestial-client
Version: 0.1
Summary: Python client for www.celestial-automl.com
Home-page: https://github.com/LarsHH/celestial-client
Author: Lars Hertel
Author-email: lars.h.hertel@gmail.com
License: UNKNOWN
Project-URL: Website, https://www.celestial-automl.com
Project-URL: Bug Tracker, https://github.com/LarsHH/celestial-client/issues
Platform: UNKNOWN
Classifier: Programming Language :: Python :: 3
Classifier: License :: OSI Approved :: MIT License
Classifier: Operating System :: OS Independent
Requires-Dist: requests
